{
  "id": "bespoke_page",
  "label": "Bespoke Page",
  "repeatable": false,
  "status": true,
  "json": {
    "Main": {
      "slices": {
        "type": "Slices",
        "fieldset": "Slice Zone",
        "config": {
          "choices": {
            "ecom_hero": {
              "type": "SharedSlice"
            },
            "explore_works": {
              "type": "SharedSlice"
            },
            "being_terrific": {
              "type": "SharedSlice"
            },
            "bespoke_tech_stack": {
              "type": "SharedSlice"
            }
          }
        }
      }
    }
  }
}