{
  "title": {
    "__TYPE__": "StructuredTextContent",
    "value": [
      {
        "type": "paragraph",
        "content": {
          "text": "Ex pariatur anim ut qui laboris dolor excepteur cillum ex. Officia do labore velit eiusmod aliqua culpa fugiat sunt dolore est minim."
        }
      }
    ]
  },
  "slices": {
    "__TYPE__": "SliceContentType",
    "value": [
      {
        "key": "hero$089752a1-2bf0-4668-ae84-2eb8c5b2d1e6",
        "name": "hero",
        "widget": {
          "__TYPE__": "SharedSliceContent",
          "variation": "default",
          "primary": {
            "title": {
              "__TYPE__": "StructuredTextContent",
              "value": [
                {
                  "type": "paragraph",
                  "content": {
                    "text": "Do non fugiat dolor. Occaecat laboris proident sit excepteur quis elit eiusmod dolore esse est quis consequat reprehenderit nulla pariatur."
                  }
                }
              ]
            },
            "description": {
              "__TYPE__": "StructuredTextContent",
              "value": [
                {
                  "type": "paragraph",
                  "content": {
                    "text": "Exercitation deserunt laboris est mollit."
                  }
                }
              ]
            },
            "highlight_description": {
              "__TYPE__": "StructuredTextContent",
              "value": [
                {
                  "type": "paragraph",
                  "content": {
                    "text": "Cillum nisi labore mollit id ipsum labore non quis. Esse sint duis duis amet enim elit elit veniam reprehenderit deserunt dolore velit deserunt deserunt laborum. Lorem deserunt nulla officia laborum labore dolor laboris."
                  }
                }
              ]
            },
            "hero_showcase_logo": {
              "__TYPE__": "ImageContent",
              "origin": {
                "id": "main",
                "url": "https://images.unsplash.com/photo-1471897488648-5eae4ac6686b",
                "width": 3560,
                "height": 5340
              },
              "url": "https://images.unsplash.com/photo-1471897488648-5eae4ac6686b",
              "width": 3560,
              "height": 5340,
              "edit": {
                "zoom": 1,
                "crop": {
                  "x": 0,
                  "y": 0
                },
                "background": "transparent"
              },
              "thumbnails": {}
            }
          },
          "items": [
            {
              "__TYPE__": "GroupItemContent",
              "value": [
                [
                  "hero_small_logo_showcase",
                  {
                    "__TYPE__": "ImageContent",
                    "origin": {
                      "id": "main",
                      "url": "https://images.unsplash.com/photo-1491975474562-1f4e30bc9468",
                      "width": 4000,
                      "height": 6000
                    },
                    "url": "https://images.unsplash.com/photo-1491975474562-1f4e30bc9468",
                    "width": 4000,
                    "height": 6000,
                    "edit": {
                      "zoom": 1,
                      "crop": {
                        "x": 0,
                        "y": 0
                      },
                      "background": "transparent"
                    },
                    "thumbnails": {}
                  }
                ]
              ]
            }
          ]
        }
      },
      {
        "key": "relationships$43401575-3929-46a1-b655-de3070d8ed2a",
        "name": "relationships",
        "widget": {
          "__TYPE__": "SharedSliceContent",
          "variation": "default",
          "primary": {},
          "items": [
            {
              "__TYPE__": "GroupItemContent",
              "value": [
                [
                  "relationships_logo_showcase",
                  {
                    "__TYPE__": "ImageContent",
                    "origin": {
                      "id": "main",
                      "url": "https://images.unsplash.com/photo-1547082299-de196ea013d6",
                      "width": 4272,
                      "height": 2848
                    },
                    "url": "https://images.unsplash.com/photo-1547082299-de196ea013d6",
                    "width": 4272,
                    "height": 2848,
                    "edit": {
                      "zoom": 1,
                      "crop": {
                        "x": 0,
                        "y": 0
                      },
                      "background": "transparent"
                    },
                    "thumbnails": {}
                  }
                ]
              ]
            }
          ]
        }
      },
      {
        "key": "scale_your_ecommerce$9400ffe0-fc36-4fff-b71b-258a8539102c",
        "name": "scale_your_ecommerce",
        "widget": {
          "__TYPE__": "SharedSliceContent",
          "variation": "default",
          "primary": {},
          "items": [
            {
              "__TYPE__": "GroupItemContent",
              "value": [
                [
                  "description",
                  {
                    "__TYPE__": "StructuredTextContent",
                    "value": [
                      {
                        "type": "paragraph",
                        "content": {
                          "text": "Cillum labore reprehenderit incididunt anim ea sint adipisicing nisi aute magna. Aliqua duis culpa pariatur consequat tempor ad sunt reprehenderit consectetur fugiat elit. Consequat elit esse consequat minim consequat nisi qui ut proident do adipisicing."
                        }
                      }
                    ]
                  }
                ],
                [
                  "logo",
                  {
                    "__TYPE__": "ImageContent",
                    "origin": {
                      "id": "main",
                      "url": "https://images.unsplash.com/photo-1496181133206-80ce9b88a853",
                      "width": 5243,
                      "height": 3495
                    },
                    "url": "https://images.unsplash.com/photo-1496181133206-80ce9b88a853",
                    "width": 5243,
                    "height": 3495,
                    "edit": {
                      "zoom": 1,
                      "crop": {
                        "x": 0,
                        "y": 0
                      },
                      "background": "transparent"
                    },
                    "thumbnails": {}
                  }
                ]
              ]
            }
          ]
        }
      },
      {
        "key": "explore_works$0892cd1f-8505-4967-b99a-1b56c85b5fe9",
        "name": "explore_works",
        "widget": {
          "__TYPE__": "SharedSliceContent",
          "variation": "default",
          "primary": {},
          "items": [
            {
              "__TYPE__": "GroupItemContent",
              "value": []
            }
          ]
        }
      },
      {
        "key": "design_showcase$2ac1e47f-547c-4b50-ba67-db16b791b290",
        "name": "design_showcase",
        "widget": {
          "__TYPE__": "SharedSliceContent",
          "variation": "default",
          "primary": {
            "title": {
              "__TYPE__": "StructuredTextContent",
              "value": [
                {
                  "type": "heading1",
                  "content": {
                    "text": "Contain"
                  }
                }
              ]
            }
          },
          "items": [
            {
              "__TYPE__": "GroupItemContent",
              "value": []
            }
          ]
        }
      }
    ]
  }
}